smahat/__init__.py
smahat/decode.py
smahat/encode.py
smahat/result.py
smahat-0.0.1.dist-info/LICENSE
smahat-0.0.1.dist-info/METADATA
smahat-0.0.1.dist-info/WHEEL
smahat-0.0.1.dist-info/top_level.txt
smahat-0.0.1.dist-info/RECORD
