Metadata-Version: 2.1
Name: smahat
Version: 0.0.1
Summary: Smahat Time Series Encoding
Home-page: https://github.com/ghilesmeddour/smahat-time-series-encoding
Author: Ghiles Meddour
Author-email: ghiles.meddour@munic.io
License: UNKNOWN
Project-URL: Bug Tracker, https://github.com/ghilesmeddour/smahat-time-series-encoding/issues
Platform: UNKNOWN
Classifier: Programming Language :: Python :: 3
Classifier: Operating System :: OS Independent
Requires-Python: >=3.8
License-File: LICENSE
Requires-Dist: bitarray
